phylab/__init__.py
phylab/lab.py
phylab/rc.py
phylab-0.4.1.data/scripts/beat.py
phylab-0.4.1.data/scripts/beat_ext.py
phylab-0.4.1.data/scripts/beat_naive.py
phylab-0.4.1.data/scripts/circfit.py
phylab-0.4.1.data/scripts/confidence_bands.py
phylab-0.4.1.data/scripts/cov19.py
phylab-0.4.1.data/scripts/damping_estimate.py
phylab-0.4.1.data/scripts/distributions.py
phylab-0.4.1.dist-info/LICENSE
phylab-0.4.1.dist-info/METADATA
phylab-0.4.1.dist-info/WHEEL
phylab-0.4.1.dist-info/top_level.txt
phylab-0.4.1.dist-info/RECORD
