Metadata-Version: 2.1
Name: phylab
Version: 0.4.1
Summary: A Python module for basic data analysis and curve fitting for Physics laboratory students.
Home-page: https://github.com/BernardoTomelleri/phylab
Author: Bernardo Tomelleri
Author-email: berni.tomelleri@gmail.com
License: GPLv3
Project-URL: Bug Tracker, https://github.com/BernardoTomelleri/phylab/issues
Platform: UNKNOWN
Classifier: Programming Language :: Python :: 3
Classifier: Intended Audience :: Education
Classifier: License :: OSI Approved :: GNU General Public License v3 or later (GPLv3+)
Classifier: Operating System :: OS Independent
Requires-Python: >=3.6
Requires-Dist: numpy
Requires-Dist: scipy
Requires-Dist: matplotlib
